snipstr/__init__.py
snipstr/base.py
snipstr/enums.py
snipstr/errors.py
snipstr/py.typed
snipstr/snipstr.py
snipstr/types.py
snipstr-1.0.1.dist-info/LICENSE
snipstr-1.0.1.dist-info/METADATA
snipstr-1.0.1.dist-info/WHEEL
snipstr-1.0.1.dist-info/RECORD
