Metadata-Version: 2.3
Name: snipstr
Version: 1.0.1
Summary: A lightweight library for easy-to-use text truncation with a friendly interface.
License: MIT
Keywords: string,truncate,shorten,snip,text-processing,formatting,utility,ellipsis,trim,cut,abbreviate,text,substring,overflow,clip,fluent-interface,method-chaining,text-manipulation
Author: Timur Valiev
Author-email: cptchunk@yandex.ru
Requires-Python: >=3.10,<4.0
Classifier: Development Status :: 5 - Production/Stable
Classifier: Intended Audience :: Developers
Classifier: License :: OSI Approved :: MIT License
Classifier: Programming Language :: Python :: 3
Classifier: Programming Language :: Python :: 3.10
Classifier: Programming Language :: Python :: 3.11
Classifier: Programming Language :: Python :: 3.12
Classifier: Programming Language :: Python :: 3.13
Classifier: Programming Language :: Python :: 3.14
Classifier: Topic :: Software Development :: Libraries :: Python Modules
Classifier: Typing :: Typed
Project-URL: Homepage, https://github.com/imtoopunkforyou/snipstr
